csvcat/__init__.py
csvcat/main.py
csvcat/tests/__init__.py
csvcat/tests/test_parse_column_nums.py
csvcat-2.0.2.dist-info/DESCRIPTION.rst
csvcat-2.0.2.dist-info/METADATA
csvcat-2.0.2.dist-info/RECORD
csvcat-2.0.2.dist-info/WHEEL
csvcat-2.0.2.dist-info/entry_points.txt
csvcat-2.0.2.dist-info/metadata.json
csvcat-2.0.2.dist-info/pbr.json
csvcat-2.0.2.dist-info/top_level.txt
