Metadata-Version: 2.0
Name: csvcat
Version: 2.0.2
Summary: Concatenate comma separated value files
Home-page: https://github.com/dhellmann/csvcat
Author: Doug hellmann
Author-email: doug@doughellmann.com
License: UNKNOWN
Platform: UNKNOWN
Classifier: Development Status :: 5 - Production/Stable
Classifier: Environment :: Console
Classifier: Intended Audience :: End Users/Desktop
Classifier: License :: OSI Approved :: Apache Software License
Classifier: Operating System :: OS Independent
Classifier: Programming Language :: Python
Classifier: Programming Language :: Python :: 2
Classifier: Programming Language :: Python :: 2.7
Classifier: Topic :: Database
Classifier: Topic :: Office/Business
Classifier: Topic :: Utilities
Requires-Dist: argparse
